topsis/__init__.py
topsis/__main__.py
Topsis_Miet_102203012-1.0.0.dist-info/LICENSE
Topsis_Miet_102203012-1.0.0.dist-info/METADATA
Topsis_Miet_102203012-1.0.0.dist-info/WHEEL
Topsis_Miet_102203012-1.0.0.dist-info/entry_points.txt
Topsis_Miet_102203012-1.0.0.dist-info/top_level.txt
Topsis_Miet_102203012-1.0.0.dist-info/RECORD
