Metadata-Version: 2.2
Name: Topsis_Miet_102203012
Version: 1.0.0
Summary: Multiple Criteria Decision Making using Topsis
Home-page: https://github.com/miet2005/Topsis_Miet_102203012
Author: Miet Pamecha
Author-email: mietpamecha10@gmail.com
License: MIT
Classifier: License :: OSI Approved :: MIT License
Classifier: Programming Language :: Python :: 3.6
Classifier: Programming Language :: Python :: 3.7
Classifier: Programming Language :: Python :: 3.8
License-File: LICENSE
Dynamic: author
Dynamic: author-email
Dynamic: classifier
Dynamic: description
Dynamic: description-content-type
Dynamic: home-page
Dynamic: license
Dynamic: summary
